savvi-0.3.1.dist-info/METADATA
savvi-0.3.1.dist-info/WHEEL
savvi-0.3.1.dist-info/entry_points.txt
savvi-0.3.1.dist-info/licenses/LICENSE
savvi/__init__.py
savvi/linear_regression.py
savvi/multinomial.py
savvi/special.py
savvi/utils.py
savvi-0.3.1.dist-info/RECORD
